passwordless/__init__.py
passwordless/client.py
passwordless_client-0.1.7.dist-info/METADATA
passwordless_client-0.1.7.dist-info/WHEEL
passwordless_client-0.1.7.dist-info/top_level.txt
passwordless_client-0.1.7.dist-info/RECORD
