Metadata-Version: 2.1
Name: passwordless-client
Version: 0.1.7
Summary: A client library for Bitwardens Passwordless.dev API
Home-page: https://github.com/yourusername/passwordless-client
Author: Matthew Fiallos
Author-email: matthew.fiallos@randstadusa.com
Classifier: Development Status :: 3 - Alpha
Classifier: Intended Audience :: Developers
Classifier: License :: OSI Approved :: MIT License
Classifier: Programming Language :: Python :: 3.6
Classifier: Programming Language :: Python :: 3.7
Classifier: Programming Language :: Python :: 3.8
Classifier: Programming Language :: Python :: 3.9
Requires-Dist: requests
